keycloak_api_manager/__init__.py
keycloak_api_manager/keycloak_api_manager.py
keycloak_api_manager-1.0.1.dist-info/LICENSE.txt
keycloak_api_manager-1.0.1.dist-info/METADATA
keycloak_api_manager-1.0.1.dist-info/WHEEL
keycloak_api_manager-1.0.1.dist-info/top_level.txt
keycloak_api_manager-1.0.1.dist-info/RECORD
