Metadata-Version: 2.1
Name: keycloak-api-manager
Version: 1.0.1
Summary: Keycloak API for management
Author-email: Polyakov Sergey <martinlauren555@gmail.com>
License: MIT License
Project-URL: Homepage, https://github.com/martinlauren55/keycloak-api-manager
Project-URL: Documentation, https://github.com/martinlauren55/keycloak-api-manager/blob/main/DOCS/DOCS.md
Project-URL: Repository, https://github.com/martinlauren55/keycloak-api-manager.git
Keywords: keycloak,API,keycloak API management
Classifier: Programming Language :: Python :: 3
Classifier: License :: OSI Approved :: MIT License
Requires-Python: >=3.5
License-File: LICENSE.txt
Requires-Dist: requests
